{
    "notices": {
        "lastPage": 1,
        "lastGetId": "D521BE00475DF824390710F83E45E3D0",
        "list": [
            {
                "completeTime": "2022-09-14 17:01:11",
                "content": "皆さん\rお疲れ。今日の宿題は以下の通りです。\r１、第3課の内容を復習してください。\r２、第3課の練習問題を完成して、「作业区」で提出してください。\r３、二人でグループになって、会話の発表を練習してください。来週の授業で発表します。\rそれでは、日本語の勉強を頑張ってくださいね。",
                "count_all": 46,
                "count_read": 41,
                "createrId": 159972368,
                "createrName": "郑盼盼",
                "createrPuid": 159972368,
                "extendParam": {
                    "cparams": "{\"funConfig\":{\"funTag\":1,\"content\":{\"courseType\":0,\"courseId\":227950209}}}",
                    "showRead": 0,
                    "showReceiver": 0,
                    "visible": 0
                },
                "idCode": "BBDA85A18FBE72BB094AA86A52FEBD38",
                "insertTime": 1663146070000,
                "isRtf": 0,
                "isread": 1,
                "logo": "http://p.ananas.chaoxing.com/star3/origin/02a6d4377246d85f904f0e92394895ee.png",
                "personStatus": 0,
                "praise_count": 3,
                "receiverArray": [
                    {
                        "clazzId": "61979211",
                        "name": "2022级（1）",
                        "type": 4,
                        "courseId": "227950209"
                    }
                ],
                "redDot": 1,
                "reqSendParams": 0,
                "sendDuration": "1秒",
                "sendTag": 0,
                "sendTime": "2022-09-14 17:01:10",
                "send_sign": 0,
                "source": 1,
                "sourceType": 14,
                "status": 0,
                "tag": "courseId227950209",
                "title": "今日の宿題について",
                "toNames": [
                    "2022级（1）"
                ],
                "toclazzs": "2022级（1）",
                "top": 0
            },
            {
                "attachment": "[{\"attachmentType\":25,\"att_web\":{\"examOrWorkId\":22050776,\"examOrWork\":\"work\",\"clazzId\":61979211,\"logo\":\"http://mooc1.chaoxing.com/images/statistic/phone/zyNew.png\",\"title\":\"第3课 课后练习\",\"courseId\":227950209,\"content\":\"09-14 16:46\",\"url\":\"https://mooc1-api.chaoxing.com/examApi/intoexamorwork?taskrefId=22050776&courseId=227950209&classId=61979211&workOrExam=work&enc=4aacd1a9207e81d0e6836c6845900a52\"},\"examOrTextId\":22050776}]",
                "completeTime": "2022-09-14 16:46:18",
                "content": "课程名称：公共日语(一)\r作业名称：第3课 课后练习\r开始时间：2022-09-14 16:45\r结束时间：2022-09-20 21:00",
                "count_all": 1,
                "count_read": 1,
                "createrId": 115013135,
                "createrName": "学习通知",
                "createrPuid": 115013135,
                "extendParam": {
                    "cparams": "{\"funConfig\":{\"funTag\":1,\"content\":{\"courseType\":0,\"courseId\":227950209}}}",
                    "showRead": 1,
                    "showReceiver": 1,
                    "visible": 0
                },
                "idCode": "AD9C85F89AFF322A1AF0DC4057EAC3B1",
                "insertTime": 1663145177000,
                "isRtf": 1,
                "isread": 1,
                "logo": "http://p.ananas.chaoxing.com/star3/origin/02a6d4377246d85f904f0e92394895ee.png",
                "personStatus": 0,
                "receiverArray": [
                    {
                        "clazzId": "61979211",
                        "name": "2022级（1）",
                        "type": 4,
                        "courseId": "227950209"
                    }
                ],
                "redDot": 1,
                "reqSendParams": 0,
                "rtf_content": "<p>课程名称：公共日语(一)</p><p>作业名称：第3课 课后练习</p><p>开始时间：2022-09-14 16:45</p><p>结束时间：2022-09-20 21:00</p></p><p><br/></p><div class=\"editor-iframe\" contenteditable=\"false\"><iframe frameborder=\"0\" scrolling=\"no\" cid=\"f26f9077-083f-4b2b-84c5-71ef80a31c16\" src=\"insertWeb.html\" name=\"{&quot;attachmentType&quot;:25,&quot;att_web&quot;:{&quot;examOrWorkId&quot;:22050776,&quot;examOrWork&quot;:&quot;work&quot;,&quot;clazzId&quot;:61979211,&quot;logo&quot;:&quot;http://mooc1.chaoxing.com/images/statistic/phone/zyNew.png&quot;,&quot;title&quot;:&quot;第3课 课后练习&quot;,&quot;courseId&quot;:227950209,&quot;content&quot;:&quot;09-14 16:46&quot;,&quot;url&quot;:&quot;https://mooc1-api.chaoxing.com/examApi/intoexamorwork?taskrefId=22050776&courseId=227950209&classId=61979211&workOrExam=work&enc=4aacd1a9207e81d0e6836c6845900a52&quot;},&quot;examOrTextId&quot;:22050776}\" class=\"attach-module attach-insertWeb\" module=\"insertWeb\"></iframe></div><p>​<br/></p>",
                "sendDuration": "1秒",
                "sendTag": 0,
                "sendTime": "2022-09-14 16:46:17",
                "send_sign": 0,
                "source": 2,
                "sourceType": 14,
                "status": 0,
                "tag": "courseId227950209",
                "title": "作业:《公共日语(一)》第3课 课后练习",
                "toNames": [
                    "2022级（1）"
                ],
                "toclazzs": "2022级（1）",
                "top": 0
            },
            {
                "completeTime": "2022-09-14 08:54:24",
                "content": "各位同学，请完成学习通上极限的定义和极限的四则运算法则两节课视频观看，复习昨天所学的内容，并进行下次课的预习。温馨提醒：视频观看完成情况系统会自动打分，计入平时成绩，请大家重视。另外，学习通资料中有教材习题选解，大家可以参考。\n",
                "count_all": 381,
                "count_read": 277,
                "createrId": 23750371,
                "createrName": "宋秀迎",
                "createrPuid": 23750371,
                "idCode": "D709E86C5738BEDFB969CC3AE410A0FD",
                "insertTime": 1663116863000,
                "isRtf": 1,
                "isread": 1,
                "logo": "http://p.ananas.chaoxing.com/star3/origin/02a6d4377246d85f904f0e92394895ee.png",
                "personStatus": 0,
                "praise_count": 0,
                "receiverArray": [
                    {
                        "clazzId": "62086592",
                        "name": "计科2201、物流2201",
                        "type": 4,
                        "courseId": "219627094"
                    },
                    {
                        "clazzId": "44164444",
                        "name": "计科2101",
                        "type": 4,
                        "courseId": "219627094"
                    },
                    {
                        "clazzId": "44164445",
                        "name": "应统2101,物流2101",
                        "type": 4,
                        "courseId": "219627094"
                    },
                    {
                        "clazzId": "44164447",
                        "name": "电商2101",
                        "type": 4,
                        "courseId": "219627094"
                    },
                    {
                        "clazzId": "61903758",
                        "name": "电商2201，应统2201",
                        "type": 4,
                        "courseId": "219627094"
                    }
                ],
                "redDot": 1,
                "replyFloor": "",
                "reqSendParams": 0,
                "rtf_content": "<p element-id=\"init\">各位同学，请完成学习通上极限的定义和极限的四则运算法则两节课视频观看，复习昨天所学的内容，并进行下次课的预习。温馨提醒：视频观看完成情况系统会自动打分，计入平时成绩，请大家重视。另外，学习通资料中有教材习题选解，大家可以参考。</p>",
                "sendDuration": "1秒",
                "sendTag": 0,
                "sendTime": "2022-09-14 08:54:23",
                "send_sign": 0,
                "source": 1,
                "sourceType": 14,
                "status": 0,
                "tag": "courseId219627094",
                "title": "学习通视频观看",
                "toNames": [
                    "计科2201、物流2201",
                    "计科2101",
                    "应统2101,物流2101",
                    "电商2101",
                    "电商2201，应统2201"
                ],
                "toclazzs": "应统2101,物流2101,计科2101,电商2101,计科2201、物流2201,电商2201，应统2201",
                "top": 0
            },
            {
                "completeTime": "2022-09-13 15:36:21",
                "content": "皆さん\nお疲れ。截至目前为止还有部分同学未在讨论区里提交自己名字的日语写法和读法。请尽快提交，作业的截止时间为今天晚上9:00前。\n",
                "count_all": 45,
                "count_read": 44,
                "createrId": 159972368,
                "createrName": "郑盼盼",
                "createrPuid": 159972368,
                "idCode": "A11BFFF81A3A67FB390710F83E45E3D0",
                "insertTime": 1663054580000,
                "isRtf": 1,
                "isread": 1,
                "logo": "http://p.ananas.chaoxing.com/star3/origin/02a6d4377246d85f904f0e92394895ee.png",
                "personStatus": 0,
                "receiverArray": [
                    {
                        "clazzId": "61979211",
                        "name": "2022级（1）",
                        "type": 4,
                        "courseId": "227950209"
                    }
                ],
                "redDot": 1,
                "reqSendParams": 0,
                "rtf_content": "<p element-id=\"init\">皆さん</p><p element-id=\"83rnvc6y\">　お疲れ。截至目前为止还有部分同学未在讨论区里提交自己名字的日语写法和读法。请尽快提交，作业的截止时间为今天晚上9:00前。</p>",
                "sendDuration": "1秒",
                "sendTag": 0,
                "sendTime": "2022-09-13 15:36:20",
                "send_sign": 0,
                "source": 1,
                "sourceType": 14,
                "status": 0,
                "tag": "courseId227950209",
                "title": "关于作业提交",
                "toNames": [
                    "2022级（1）"
                ],
                "toclazzs": "2022级（1）",
                "top": 0
            },
            {
                "attachment": "[{\"attachmentType\":25,\"att_web\":{\"examOrWorkId\":22013117,\"examOrWork\":\"work\",\"clazzId\":62385335,\"logo\":\"http://mooc1.chaoxing.com/images/statistic/phone/zyNew.png\",\"title\":\"第一章 进入近代后中华民族的磨难与抗争\",\"courseId\":228130181,\"content\":\"09-12 12:07\",\"url\":\"https://mooc1-api.chaoxing.com/examApi/intoexamorwork?taskrefId=22013117&courseId=228130181&classId=62385335&workOrExam=work&enc=be349a2e97e46b4816b5bb55e09b4f07\"},\"examOrTextId\":22013117}]",
                "completeTime": "2022-09-12 12:07:36",
                "content": "课程名称：中国近现代史纲要\r作业名称：第一章 进入近代后中华民族的磨难与抗争\r开始时间：2022-09-12 12:06\r结束时间：2023-01-06 12:06",
                "count_all": 1,
                "count_read": 1,
                "createrId": 115013135,
                "createrName": "学习通知",
                "createrPuid": 115013135,
                "extendParam": {
                    "cparams": "{\"funConfig\":{\"funTag\":1,\"content\":{\"courseType\":0,\"courseId\":228130181}}}",
                    "showRead": 1,
                    "showReceiver": 1,
                    "visible": 0
                },
                "idCode": "E5601F700DB52EB0094AA86A52FEBD38",
                "insertTime": 1662955655000,
                "isRtf": 1,
                "isread": 1,
                "logo": "http://p.ananas.chaoxing.com/star3/origin/02a6d4377246d85f904f0e92394895ee.png",
                "personStatus": 0,
                "receiverArray": [
                    {
                        "clazzId": "62385335",
                        "name": "计科2201,物流2201",
                        "type": 4,
                        "courseId": "228130181"
                    }
                ],
                "redDot": 1,
                "reqSendParams": 0,
                "rtf_content": "<p>课程名称：中国近现代史纲要</p><p>作业名称：第一章 进入近代后中华民族的磨难与抗争</p><p>开始时间：2022-09-12 12:06</p><p>结束时间：2023-01-06 12:06</p></p><p><br/></p><div class=\"editor-iframe\" contenteditable=\"false\"><iframe frameborder=\"0\" scrolling=\"no\" cid=\"be280c66-11bb-47f0-9d77-189ce3b5ec12\" src=\"insertWeb.html\" name=\"{&quot;attachmentType&quot;:25,&quot;att_web&quot;:{&quot;examOrWorkId&quot;:22013117,&quot;examOrWork&quot;:&quot;work&quot;,&quot;clazzId&quot;:62385335,&quot;logo&quot;:&quot;http://mooc1.chaoxing.com/images/statistic/phone/zyNew.png&quot;,&quot;title&quot;:&quot;第一章 进入近代后中华民族的磨难与抗争&quot;,&quot;courseId&quot;:228130181,&quot;content&quot;:&quot;09-12 12:07&quot;,&quot;url&quot;:&quot;https://mooc1-api.chaoxing.com/examApi/intoexamorwork?taskrefId=22013117&courseId=228130181&classId=62385335&workOrExam=work&enc=be349a2e97e46b4816b5bb55e09b4f07&quot;},&quot;examOrTextId&quot;:22013117}\" class=\"attach-module attach-insertWeb\" module=\"insertWeb\"></iframe></div><p>​<br/></p>",
                "sendDuration": "1秒",
                "sendTag": 0,
                "sendTime": "2022-09-12 12:07:35",
                "send_sign": 0,
                "source": 2,
                "sourceType": 14,
                "status": 0,
                "tag": "courseId228130181",
                "title": "作业:《中国近现代史纲要》第一章 进入近代后中华民族的磨难与抗争",
                "toNames": [
                    "计科2201,物流2201"
                ],
                "toclazzs": "计科2201,物流2201",
                "top": 0
            },
            {
                "attachment": "[{\"attachmentType\":25,\"att_web\":{\"examOrWorkId\":22013063,\"examOrWork\":\"work\",\"clazzId\":62385335,\"logo\":\"http://mooc1.chaoxing.com/images/statistic/phone/zyNew.png\",\"title\":\"导言\",\"courseId\":228130181,\"content\":\"09-12 12:05\",\"url\":\"https://mooc1-api.chaoxing.com/examApi/intoexamorwork?taskrefId=22013063&courseId=228130181&classId=62385335&workOrExam=work&enc=9c4fdc692848646b8bd229f01b9dbc3a\"},\"examOrTextId\":22013063}]",
                "completeTime": "2022-09-12 12:05:27",
                "content": "课程名称：中国近现代史纲要\r作业名称：导言\r开始时间：2022-09-12 12:01\r结束时间：2023-01-06 12:01",
                "count_all": 1,
                "count_read": 1,
                "createrId": 115013135,
                "createrName": "学习通知",
                "createrPuid": 115013135,
                "extendParam": {
                    "cparams": "{\"funConfig\":{\"funTag\":1,\"content\":{\"courseType\":0,\"courseId\":228130181}}}",
                    "showRead": 1,
                    "showReceiver": 1,
                    "visible": 0
                },
                "idCode": "82303535A4687F36094AA86A52FEBD38",
                "insertTime": 1662955527000,
                "isRtf": 1,
                "isread": 1,
                "logo": "http://p.ananas.chaoxing.com/star3/origin/02a6d4377246d85f904f0e92394895ee.png",
                "personStatus": 0,
                "receiverArray": [
                    {
                        "clazzId": "62385335",
                        "name": "计科2201,物流2201",
                        "type": 4,
                        "courseId": "228130181"
                    }
                ],
                "redDot": 1,
                "reqSendParams": 0,
                "rtf_content": "<p>课程名称：中国近现代史纲要</p><p>作业名称：导言</p><p>开始时间：2022-09-12 12:01</p><p>结束时间：2023-01-06 12:01</p></p><p><br/></p><div class=\"editor-iframe\" contenteditable=\"false\"><iframe frameborder=\"0\" scrolling=\"no\" cid=\"c20c8185-1294-4c8a-ac18-08ea1bef50f0\" src=\"insertWeb.html\" name=\"{&quot;attachmentType&quot;:25,&quot;att_web&quot;:{&quot;examOrWorkId&quot;:22013063,&quot;examOrWork&quot;:&quot;work&quot;,&quot;clazzId&quot;:62385335,&quot;logo&quot;:&quot;http://mooc1.chaoxing.com/images/statistic/phone/zyNew.png&quot;,&quot;title&quot;:&quot;导言&quot;,&quot;courseId&quot;:228130181,&quot;content&quot;:&quot;09-12 12:05&quot;,&quot;url&quot;:&quot;https://mooc1-api.chaoxing.com/examApi/intoexamorwork?taskrefId=22013063&courseId=228130181&classId=62385335&workOrExam=work&enc=9c4fdc692848646b8bd229f01b9dbc3a&quot;},&quot;examOrTextId&quot;:22013063}\" class=\"attach-module attach-insertWeb\" module=\"insertWeb\"></iframe></div><p>​<br/></p>",
                "sendDuration": "",
                "sendTag": 0,
                "sendTime": "2022-09-12 12:05:27",
                "send_sign": 0,
                "source": 2,
                "sourceType": 14,
                "status": 0,
                "tag": "courseId228130181",
                "title": "作业:《中国近现代史纲要》导言",
                "toNames": [
                    "计科2201,物流2201"
                ],
                "toclazzs": "计科2201,物流2201",
                "top": 0
            },
            {
                "attachment": "[{\"attachmentType\":25,\"att_web\":{\"examOrWorkId\":21886756,\"examOrWork\":\"work\",\"clazzId\":62086592,\"logo\":\"http://mooc1.chaoxing.com/images/statistic/phone/zyNew.png\",\"title\":\"第一章函数作业\",\"courseId\":219627094,\"content\":\"09-08 12:05\",\"url\":\"https://mooc1-api.chaoxing.com/examApi/intoexamorwork?taskrefId=21886756&courseId=219627094&classId=62086592&workOrExam=work&enc=55ec8da91b3828bf99f87e052d795bca\"},\"examOrTextId\":21886756}]",
                "completeTime": "2022-09-08 12:05:04",
                "content": "课程名称：高等数学(上)\r作业名称：第一章函数作业\r开始时间：2022-09-08 12:05\r结束时间：2022-09-15 23:55",
                "count_all": 1,
                "count_read": 1,
                "createrId": 115013135,
                "createrName": "学习通知",
                "createrPuid": 115013135,
                "extendParam": {
                    "cparams": "{\"funConfig\":{\"funTag\":1,\"content\":{\"courseType\":0,\"courseId\":219627094}}}",
                    "showRead": 1,
                    "showReceiver": 1,
                    "visible": 0
                },
                "idCode": "99CE3C24BA5635DFB969CC3AE410A0FD",
                "insertTime": 1662609903000,
                "isRtf": 1,
                "isread": 1,
                "logo": "http://p.ananas.chaoxing.com/star3/origin/02a6d4377246d85f904f0e92394895ee.png",
                "personStatus": 0,
                "receiverArray": [
                    {
                        "clazzId": "62086592",
                        "name": "计科2201、物流2201",
                        "type": 4,
                        "courseId": "219627094"
                    }
                ],
                "redDot": 1,
                "reqSendParams": 0,
                "rtf_content": "<p>课程名称：高等数学(上)</p><p>作业名称：第一章函数作业</p><p>开始时间：2022-09-08 12:05</p><p>结束时间：2022-09-15 23:55</p></p><p><br/></p><div class=\"editor-iframe\" contenteditable=\"false\"><iframe frameborder=\"0\" scrolling=\"no\" cid=\"a0dde8b0-ec5e-4fe3-aeb5-5657994317a2\" src=\"insertWeb.html\" name=\"{&quot;attachmentType&quot;:25,&quot;att_web&quot;:{&quot;examOrWorkId&quot;:21886756,&quot;examOrWork&quot;:&quot;work&quot;,&quot;clazzId&quot;:62086592,&quot;logo&quot;:&quot;http://mooc1.chaoxing.com/images/statistic/phone/zyNew.png&quot;,&quot;title&quot;:&quot;第一章函数作业&quot;,&quot;courseId&quot;:219627094,&quot;content&quot;:&quot;09-08 12:05&quot;,&quot;url&quot;:&quot;https://mooc1-api.chaoxing.com/examApi/intoexamorwork?taskrefId=21886756&courseId=219627094&classId=62086592&workOrExam=work&enc=55ec8da91b3828bf99f87e052d795bca&quot;},&quot;examOrTextId&quot;:21886756}\" class=\"attach-module attach-insertWeb\" module=\"insertWeb\"></iframe></div><p>​<br/></p>",
                "sendDuration": "1秒",
                "sendTag": 0,
                "sendTime": "2022-09-08 12:05:03",
                "send_sign": 0,
                "source": 2,
                "sourceType": 14,
                "status": 0,
                "tag": "courseId219627094",
                "title": "作业:《高等数学(上)》第一章函数作业",
                "toNames": [
                    "计科2201、物流2201"
                ],
                "toclazzs": "计科2201、物流2201",
                "top": 0
            },
            {
                "attachment": "",
                "completeTime": "2022-09-07 18:17:05",
                "content": "皆さん\r　お疲れ様。今日の宿題は以下の通りです。\r①自己紹介を準備してください。来週の授業で発表します。\r②自分の名前は日本語でどう書くか、どう読むかについて調べてください。そして、「讨论区」でコメントしてください。\r何かわからないことがあったら、聞いてくださいね。",
                "count_all": 49,
                "count_read": 47,
                "createrId": 159972368,
                "createrName": "郑盼盼",
                "createrPuid": 159972368,
                "extendParam": {
                    "cparams": "{\"funConfig\":{\"funTag\":1,\"content\":{\"courseType\":0,\"courseId\":227950209}}}",
                    "showRead": 0,
                    "showReceiver": 0,
                    "visible": 0
                },
                "idCode": "D521BE00475DF824390710F83E45E3D0",
                "insertTime": 1662545824000,
                "isRtf": 0,
                "isread": 1,
                "logo": "http://p.ananas.chaoxing.com/star3/origin/02a6d4377246d85f904f0e92394895ee.png",
                "personStatus": 0,
                "praise_count": 3,
                "receiverArray": [
                    {
                        "clazzId": "61979211",
                        "name": "2022级（1）",
                        "type": 4,
                        "courseId": "227950209"
                    }
                ],
                "redDot": 1,
                "reqSendParams": 0,
                "sendDuration": "1秒",
                "sendTag": 0,
                "sendTime": "2022-09-07 18:17:04",
                "send_sign": 0,
                "source": 1,
                "sourceType": 14,
                "status": 0,
                "tag": "courseId227950209",
                "title": "今日の宿題について",
                "toNames": [
                    "2022级（1）"
                ],
                "toclazzs": "2022级（1）",
                "top": 0
            }
        ]
    },
    "folders": [],
    "mySendNoticeCount": 0,
    "status": true
}